docrun/__init__.py
docrun/__main__.py
docrun/en.py
docrun/kernels.py
docrun/lang.py
docrun/server_kernel.py
docrun/server_ssh.py
docrun/version.py
docrun/zh.py
docrun-3.2.2.0.dist-info/LICENSE
docrun-3.2.2.0.dist-info/METADATA
docrun-3.2.2.0.dist-info/WHEEL
docrun-3.2.2.0.dist-info/top_level.txt
docrun-3.2.2.0.dist-info/RECORD
