Metadata-Version: 2.1
Name: docrun
Version: 3.2.2.0
Summary: Package for https://doc.run
Home-page: https://doc.run
Author: Xiao, Hu
Author-email: service@ovo.ltd
License: UNKNOWN
Platform: UNKNOWN
Classifier: Programming Language :: Python :: 3
Classifier: License :: OSI Approved :: MIT License
Classifier: Operating System :: OS Independent
License-File: LICENSE
Requires-Dist: websockets
Requires-Dist: paramiko
Requires-Dist: psutil
Requires-Dist: ipykernel
Requires-Dist: matlab-kernel
Requires-Dist: powershell-kernel
Requires-Dist: bash-kernel
